quick_templates.py
quick_templates-1.0.0.dist-info/WHEEL
quick_templates-1.0.0.dist-info/METADATA
quick_templates-1.0.0.dist-info/RECORD
