Metadata-Version: 2.1
Name: quick-templates
Version: 1.0.0
Summary: quickly create templates on Pug, Twig, Blade
Author: matyukov stas
Author-email: matyukov_stas@mail.ru
Requires-Python: >=3.7,<4.0
Classifier: Programming Language :: Python :: 3
Classifier: Programming Language :: Python :: 3.7
Classifier: Programming Language :: Python :: 3.8
Classifier: Programming Language :: Python :: 3.9
